{
	"_guid_": "NoC_Case_Data_With_Org_Policies",
	"_extends_": "NoC_Case_Data",

	"applicantOrganisationPolicy": {
		"OrgPolicyReference": "ApplicantPolicy",
		"OrgPolicyCaseAssignedRole": "[ApplicantSolicitor]",
		"Organisation": {
			"OrganisationID": "",
			"OrganisationName": ""
		}
	},
	"respondentOrganisationPolicy": {
		"OrgPolicyReference": "RespondentPolicy",
		"OrgPolicyCaseAssignedRole": "[RespondentSolicitor]",
		"Organisation": {
			"OrganisationID": ""
		}
	},
	"otherPartyOrganisationPolicy": {
		"OrgPolicyReference": "OtherPartyPolicy",
		"OrgPolicyCaseAssignedRole": "[OtherPartySolicitor]",
		"Organisation": {
			"OrganisationID": ""
		}
	}

}
